qcserenity/fragment.py
qcserenity/serenipy.so
qcserenity/cubeUtils.py
qcserenity/__init__.py
qcserenity/holeParticleCorrelation.py
qcserenity/redirectOutput.py
qcserenity/showCube.py
qcserenity/couple.py
qcserenity/twoDimheatMap.py
qcserenity/spectrum.py
qcserenity/tests/__init__.py
qcserenity/tests/run_all_tests.py
qcserenity/tests/test_tasks.py
qcserenity/tests/test_import.py
share/serenity/data/basis/AUG-CC-PVTZ-RI-C
share/serenity/data/basis/6-31GSS
share/serenity/data/basis/6-31+GSS
share/serenity/data/basis/AUG-CC-PV5Z
share/serenity/data/basis/DEF2-TZVP
share/serenity/data/basis/6-31+GS
share/serenity/data/basis/AUG-CC-PVQZ-RI-C
share/serenity/data/basis/STO-3G
share/serenity/data/basis/CC-PVTZ-RI-C
share/serenity/data/basis/DEF2-TZVPD
share/serenity/data/basis/6-31++GSS
share/serenity/data/basis/6-31GS
share/serenity/data/basis/CC-PVDZ-RI-C
share/serenity/data/basis/6-311+GSS
share/serenity/data/basis/MINPARKER_SP
share/serenity/data/basis/6-311+GS
share/serenity/data/basis/CC-PVQZ
share/serenity/data/basis/D-AUG-CC-PV5Z
share/serenity/data/basis/CC-PV5Z
share/serenity/data/basis/6-31++GS
share/serenity/data/basis/DEF2-TZVPP-RI-C
share/serenity/data/basis/DEF2-UNIVERSAL-JKFIT
share/serenity/data/basis/AUG-CC-PV6Z
share/serenity/data/basis/4-31G
share/serenity/data/basis/MINAO
share/serenity/data/basis/CC-PV5Z-RI-C
share/serenity/data/basis/DEF2-SVP
share/serenity/data/basis/AUG-CC-PV5Z-RI-C
share/serenity/data/basis/DEF2-SV_P_
share/serenity/data/basis/DEF2-TZVPD-RI-C
share/serenity/data/basis/3-21G
share/serenity/data/basis/DEF2-TZVPPD-RI-C
share/serenity/data/basis/6-311+G
share/serenity/data/basis/DEF2-SV_P_-RI-C
share/serenity/data/basis/6-31+G
share/serenity/data/basis/6-311GS
share/serenity/data/basis/MINPARKER_S
share/serenity/data/basis/CC-PV6Z-RI-C
share/serenity/data/basis/AUG-CC-PVTZ
share/serenity/data/basis/DEF2-TZVP-RI-C
share/serenity/data/basis/CC-PVDZ
share/serenity/data/basis/STO-6G
qcserenity-1.6.3.post2.dist-info/RECORD
qcserenity-1.6.3.post2.dist-info/WHEEL
qcserenity-1.6.3.post2.dist-info/METADATA
qcserenity-1.6.3.post2.dist-info/licenses/LICENSE
qcserenity-1.6.3.post2.dist-info/licenses/libxc/CITATION
qcserenity-1.6.3.post2.dist-info/licenses/libxc/COPYING
qcserenity-1.6.3.post2.dist-info/licenses/gtest/LICENSE
qcserenity-1.6.3.post2.dist-info/licenses/laplace-minimax/LICENSE
qcserenity-1.6.3.post2.dist-info/licenses/laplace-minimax/README.md
qcserenity-1.6.3.post2.dist-info/licenses/ecpint/CITATION
qcserenity-1.6.3.post2.dist-info/licenses/ecpint/LICENSE
qcserenity-1.6.3.post2.dist-info/licenses/mkl/license.txt
qcserenity-1.6.3.post2.dist-info/licenses/xcfun/LICENSE.md
qcserenity-1.6.3.post2.dist-info/licenses/eigen/COPYING.MPL2
qcserenity-1.6.3.post2.dist-info/licenses/eigen/COPYING.LGPL
qcserenity-1.6.3.post2.dist-info/licenses/libint/LICENSE
