Metadata-Version: 2.2
Name: qcserenity
Version: 1.6.3.post2
Summary: A quantum chemistry program focused on subsystems and embedding
Author-Email: "University of Muenster, Neugebauer Group" <serenity@uni-muenster.de>
Classifier: Programming Language :: Python :: 3
Classifier: Programming Language :: Python :: 3.7
Classifier: Programming Language :: Python :: 3.8
Classifier: Programming Language :: Python :: 3.9
Classifier: Programming Language :: Python :: 3.10
Classifier: Programming Language :: Python :: 3.11
Classifier: Programming Language :: Python :: 3.12
Classifier: Programming Language :: Python :: 3.13
Classifier: License :: OSI Approved :: GNU Lesser General Public License v3 or later (LGPLv3+)
Classifier: Operating System :: POSIX
Classifier: Operating System :: Unix
Classifier: Topic :: Scientific/Engineering :: Chemistry
Classifier: Topic :: Scientific/Engineering :: Physics
Classifier: Intended Audience :: Science/Research
Classifier: Development Status :: 5 - Production/Stable
Project-URL: Homepage, https://github.com/qcserenity/serenity
Project-URL: Issues, https://github.com/qcserenity/serenity/issues
Project-URL: Repository, https://github.com/qcserenity/serenity
Requires-Python: >=3.7
Requires-Dist: numpy
Requires-Dist: mkl==2024.2
Provides-Extra: plotting
Requires-Dist: matplotlib; extra == "plotting"
Provides-Extra: heatmap
Requires-Dist: ase; extra == "heatmap"
Requires-Dist: scipy; extra == "heatmap"
Provides-Extra: visualization
Requires-Dist: py3Dmol; extra == "visualization"
Requires-Dist: ipywidgets; extra == "visualization"
Provides-Extra: all
Requires-Dist: matplotlib; extra == "all"
Requires-Dist: ase; extra == "all"
Requires-Dist: scipy; extra == "all"
Requires-Dist: py3Dmol; extra == "all"
Requires-Dist: ipywidgets; extra == "all"
